cv_resume_builder_mcp/__init__.py
cv_resume_builder_mcp/server.py
cv_resume_builder_mcp-1.1.2.dist-info/METADATA
cv_resume_builder_mcp-1.1.2.dist-info/WHEEL
cv_resume_builder_mcp-1.1.2.dist-info/entry_points.txt
cv_resume_builder_mcp-1.1.2.dist-info/licenses/LICENSE
cv_resume_builder_mcp-1.1.2.dist-info/RECORD
