Metadata-Version: 2.4
Name: cv-resume-builder-mcp
Version: 1.1.2
Summary: AI-powered CV and resume builder using Model Context Protocol. Automatically generates and updates your CV/resume from git commits, Jira tickets, Credly badges, and LinkedIn profile.
Project-URL: Homepage, https://github.com/eyaab/cv-resume-builder-mcp
Project-URL: Documentation, https://github.com/eyaab/cv-resume-builder-mcp#readme
Project-URL: Repository, https://github.com/eyaab/cv-resume-builder-mcp
Project-URL: Issues, https://github.com/eyaab/cv-resume-builder-mcp/issues
Author: CV Resume Builder MCP Contributors
License: MIT
License-File: LICENSE
Keywords: ai,automation,career,credly,cv,cv-builder,git,jira,latex,linkedin,mcp,model-context-protocol,pdf,resume,resume-builder
Classifier: Development Status :: 4 - Beta
Classifier: Intended Audience :: Developers
Classifier: License :: OSI Approved :: MIT License
Classifier: Programming Language :: Python :: 3
Classifier: Programming Language :: Python :: 3.10
Classifier: Programming Language :: Python :: 3.11
Classifier: Programming Language :: Python :: 3.12
Classifier: Topic :: Office/Business
Classifier: Topic :: Software Development :: Libraries :: Python Modules
Requires-Python: >=3.10
Requires-Dist: httpx>=0.27.0
Requires-Dist: mcp>=0.9.0
Requires-Dist: pypdf>=4.0.0
Provides-Extra: dev
Requires-Dist: black>=24.0.0; extra == 'dev'
Requires-Dist: pytest-asyncio>=0.23.0; extra == 'dev'
Requires-Dist: pytest>=8.0.0; extra == 'dev'
Requires-Dist: ruff>=0.3.0; extra == 'dev'
